echointel/__init__.py
echointel/async_client.py
echointel/client.py
echointel/endpoints.py
echointel/py.typed
echointel/route_resolver.py
echointel/exceptions/__init__.py
echointel/exceptions/authentication.py
echointel/exceptions/base.py
echointel/exceptions/validation.py
echointel/responses/__init__.py
echointel/responses/admin.py
echointel/responses/anomaly.py
echointel/responses/attribution.py
echointel/responses/base.py
echointel/responses/churn.py
echointel/responses/credit_risk.py
echointel/responses/cross_sell.py
echointel/responses/customer.py
echointel/responses/forecast.py
echointel/responses/inventory.py
echointel/responses/journey.py
echointel/responses/pricing.py
echointel/responses/propensity.py
echointel/responses/recommendation.py
echointel/responses/sentiment.py
echointel-1.0.0.dist-info/METADATA
echointel-1.0.0.dist-info/WHEEL
echointel-1.0.0.dist-info/RECORD
