Metadata-Version: 2.4
Name: echointel
Version: 1.0.0
Summary: Python SDK for integrating with the EchoIntel AI API
Project-URL: Homepage, https://echosistema.live
Project-URL: Documentation, https://docs.echosistema.live
Project-URL: Repository, https://github.com/echosistema/echointel-sdk
Project-URL: Issues, https://github.com/echosistema/echointel-sdk/issues
Author-email: EchoIntel <dev@echosistema.live>
License-Expression: MIT
Keywords: ai,analytics,customer-segmentation,echointel,forecasting,machine-learning,sdk
Classifier: Development Status :: 5 - Production/Stable
Classifier: Intended Audience :: Developers
Classifier: License :: OSI Approved :: MIT License
Classifier: Operating System :: OS Independent
Classifier: Programming Language :: Python :: 3
Classifier: Programming Language :: Python :: 3.10
Classifier: Programming Language :: Python :: 3.11
Classifier: Programming Language :: Python :: 3.12
Classifier: Programming Language :: Python :: 3.13
Classifier: Topic :: Scientific/Engineering :: Artificial Intelligence
Classifier: Topic :: Software Development :: Libraries :: Python Modules
Classifier: Typing :: Typed
Requires-Python: >=3.10
Requires-Dist: httpx>=0.24.0
Requires-Dist: tenacity>=8.0.0
Provides-Extra: dev
Requires-Dist: mypy>=1.0.0; extra == 'dev'
Requires-Dist: pytest-asyncio>=0.21.0; extra == 'dev'
Requires-Dist: pytest-cov>=4.0.0; extra == 'dev'
Requires-Dist: pytest>=7.0.0; extra == 'dev'
Requires-Dist: respx>=0.20.0; extra == 'dev'
Requires-Dist: ruff>=0.1.0; extra == 'dev'
